mesh2depth_gpu/__init__.py
mesh2depth_gpu/camera.py
mesh2depth_gpu/convert.py
mesh2depth_gpu/depthmap.py
mesh2depth_gpu/mesh.py
mesh2depth_gpu/render.py
mesh2depth_gpu/shader.py
mesh2depth_gpu/version.py
mesh2depth_gpu/shaders/mesh.frag
mesh2depth_gpu/shaders/mesh.vert
mesh2depth_gpu-0.0.2.dist-info/LICENSE
mesh2depth_gpu-0.0.2.dist-info/METADATA
mesh2depth_gpu-0.0.2.dist-info/WHEEL
mesh2depth_gpu-0.0.2.dist-info/top_level.txt
mesh2depth_gpu-0.0.2.dist-info/RECORD
