Metadata-Version: 2.1
Name: mesh2depth_gpu
Version: 0.0.2
Summary: Fast depthmap generation using headless rendering
Author: Hyeontae Son
Author-email: countywest@naver.com
License: MIT
Platform: any
License-File: LICENSE
Requires-Dist: numpy
Requires-Dist: PyOpenGL
Requires-Dist: PyGLM
Requires-Dist: nptyping
Requires-Dist: glcontext
Requires-Dist: dacite
